ldtkpy/__init__.py
ldtkpy/api.py
ldtkpy-1.4.1.dist-info/METADATA
ldtkpy-1.4.1.dist-info/WHEEL
ldtkpy-1.4.1.dist-info/RECORD
